werkflow_metrikflow/__init__.py
werkflow_metrikflow/metrikflow.py
werkflow_metrikflow-0.2.1.dist-info/licenses/LICENSE
werkflow_metrikflow-0.2.1.dist-info/METADATA
werkflow_metrikflow-0.2.1.dist-info/WHEEL
werkflow_metrikflow-0.2.1.dist-info/top_level.txt
werkflow_metrikflow-0.2.1.dist-info/RECORD
