Metadata-Version: 2.4
Name: werkflow-metrikflow
Version: 0.2.1
Summary: A library for processing and sending metrics.
Author-email: Ada Lundhe <adalundhe@lundhe.audio>
License: MIT License
Project-URL: Homepage, https://github.com/adalundhe/werkflow-modules/tree/main/werkflow-metrikflow
Keywords: pypi,cicd,python,werkflow,workflow,metrikflow,stats,stats-integrations,datadog,reporting
Classifier: Programming Language :: Python :: 3.10
Classifier: Programming Language :: Python :: 3.11
Classifier: Programming Language :: Python :: 3.12
Classifier: License :: OSI Approved :: MIT License
Classifier: Operating System :: OS Independent
Requires-Python: >=3.10
License-File: LICENSE
Requires-Dist: metrikflow
Requires-Dist: werkflow-core
Requires-Dist: werkflow-file
Requires-Dist: werkflow-secrets
Requires-Dist: werkflow-shell
Requires-Dist: werkflow-system
Dynamic: license-file
